{
  "created": 0,
  "updated": 6,
  "total": 6,
  "country_scope": "country",
  "country_code": "DE",
  "items": [
    {
      "slug": "consumer-free-monthly",
      "period": "monthly",
      "id": "a36c11a2-21de-481d-88c3-78bfce3a149f"
    },
    {
      "slug": "consumer-free-yearly",
      "period": "yearly",
      "id": "f7a9432e-58e2-4825-bee6-8dc095c32e98"
    },
    {
      "slug": "dealer-pro-monthly",
      "period": "monthly",
      "id": "2125d24c-ae96-454d-adb6-8d99b427fd5b"
    },
    {
      "slug": "dealer-pro-yearly",
      "period": "yearly",
      "id": "f77e89ad-4aff-4e83-b89e-9113d698a3a3"
    },
    {
      "slug": "dealer-enterprise-monthly",
      "period": "monthly",
      "id": "cf97da51-d3be-4f05-b2ef-c116ccb6f2f0"
    },
    {
      "slug": "dealer-enterprise-yearly",
      "period": "yearly",
      "id": "c81f6ccf-e142-46bf-9990-f744d6d018d8"
    }
  ]
}